Topsis/__init__.py
Topsis/__main__.py
Topsis_Jitesh_Garg_102017180-1.0.0.dist-info/LICENSE
Topsis_Jitesh_Garg_102017180-1.0.0.dist-info/METADATA
Topsis_Jitesh_Garg_102017180-1.0.0.dist-info/WHEEL
Topsis_Jitesh_Garg_102017180-1.0.0.dist-info/entry_points.txt
Topsis_Jitesh_Garg_102017180-1.0.0.dist-info/top_level.txt
Topsis_Jitesh_Garg_102017180-1.0.0.dist-info/RECORD
