Metadata-Version: 2.1
Name: Topsis-Jitesh-Garg-102017180
Version: 1.0.0
Summary: A Python package for handling problems of Multiple Criteria Decision Making(MCDM) for a given dataset.
Author: Jitesh Garg
Author-email: jgarg_be20@thapar.edu
License: MIT
Classifier: Development Status :: 3 - Alpha
Classifier: Intended Audience :: Developers
Classifier: Topic :: Software Development :: Build Tools
Classifier: License :: OSI Approved :: MIT License
Classifier: Programming Language :: Python :: 3.6
Classifier: Programming Language :: Python :: 3.7
Classifier: Programming Language :: Python :: 3.8
License-File: LICENSE
Requires-Dist: numpy
Requires-Dist: pandas
